setup.py
pyzk.egg-info/PKG-INFO
pyzk.egg-info/SOURCES.txt
pyzk.egg-info/dependency_links.txt
pyzk.egg-info/not-zip-safe
pyzk.egg-info/top_level.txt
zk/__init__.py
zk/attendance.py
zk/base.py
zk/const.py
zk/exception.py
zk/user.py